odoo10_addon_product_standard_margin-10.0.1.0.0.99.dev5-py3.8-nspkg.pth
odoo/addons/product_standard_margin/README.rst
odoo/addons/product_standard_margin/__init__.py
odoo/addons/product_standard_margin/__manifest__.py
odoo/addons/product_standard_margin/data/decimal_precision.xml
odoo/addons/product_standard_margin/demo/product_product.xml
odoo/addons/product_standard_margin/i18n/es.po
odoo/addons/product_standard_margin/i18n/fr.po
odoo/addons/product_standard_margin/i18n/nl.po
odoo/addons/product_standard_margin/i18n/product_standard_margin.pot
odoo/addons/product_standard_margin/models/__init__.py
odoo/addons/product_standard_margin/models/product_product.py
odoo/addons/product_standard_margin/readme/CONTRIBUTORS.rst
odoo/addons/product_standard_margin/readme/DESCRIPTION.rst
odoo/addons/product_standard_margin/static/description/icon.png
odoo/addons/product_standard_margin/static/description/index.html
odoo/addons/product_standard_margin/tests/__init__.py
odoo/addons/product_standard_margin/tests/test_product_standard_margin.py
odoo/addons/product_standard_margin/views/product_view.xml
odoo10_addon_product_standard_margin-10.0.1.0.0.99.dev5.dist-info/METADATA
odoo10_addon_product_standard_margin-10.0.1.0.0.99.dev5.dist-info/WHEEL
odoo10_addon_product_standard_margin-10.0.1.0.0.99.dev5.dist-info/namespace_packages.txt
odoo10_addon_product_standard_margin-10.0.1.0.0.99.dev5.dist-info/top_level.txt
odoo10_addon_product_standard_margin-10.0.1.0.0.99.dev5.dist-info/RECORD
